{"visible_type": 0, "visible_list_id": 0, "time": "2022-03-03 09:07:44", "mid": "4742861093077134", "mblogid": "LhZ0NcUvc", "uid": 2771074184, "name": "全球热门搞笑排行榜", "profile_image_url": "https://tva1.sinaimg.cn/crop.0.0.180.180.50/a52b3c88jw1e8qgp5bmzyj2050050aa8.jpg?KID=imgbed,tva&Expires=1646520902&ssig=bmMpfdMWCI", "profile_url": "/u/2771074184", "verified": true, "verified_type": 0, "domain": "ssvsmr", "weihao": "", "verified_type_ext": 1, "avatar_large": "https://tva1.sinaimg.cn/crop.0.0.180.180.180/a52b3c88jw1e8qgp5bmzyj2050050aa8.jpg?KID=imgbed,tva&Expires=1646520902&ssig=4PZEPR2fsk", "avatar_hd": "https://tva1.sinaimg.cn/crop.0.0.180.180.1024/a52b3c88jw1e8qgp5bmzyj2050050aa8.jpg?KID=imgbed,tva&Expires=1646520902&ssig=qaSxXp%2BxdY", "follow_me": false, "following": false, "mbrank": 7, "mbtype": 12, "planet_video": false, "icon_list": [{"type": "vip", "data": {"mbrank": 7, "mbtype": 12}}], "can_edit": false, "textLength": 82, "source": "微博视频号", "favorited": false, "cardid": null, "pic_ids": [], "geo": null, "pic_num": 0, "is_paid": false, "mblog_vip_type": 0, "reposts_count": 1011, "comments_count": 1523, "attitudes_count": 4559, "attitudes_status": 0, "isLongText": false, "mlevel": 0, "content_auth": 0, "is_show_bulletin": 2, "mblogtype": 0, "showFeedRepost": false, "showFeedComment": false, "pictureViewerSign": false, "showPictureViewer": false, "repost_type": null, "share_repost_type": 0, "text": "#沈腾智商#接词一句不差，贾玲：买题了？捡漏太机智。[哈哈]   http://t.cn/A662cJdu ​ ​​​"}